{
  "metadata": {
    "timestamp": "2025-12-06 23:49:50",
    "job_posting_id": "4325939213",
    "job_title": "Senior Data Engineer (SQL, Python, Snowflake)",
    "company_name": "Tata Consultancy Services",
    "job_location": "Cupertino, CA",
    "pass_name": "pass3",
    "model_id": "minimax.minimax-m2"
  },
  "result": {
    "analysis": {
      "company_maturity": {
        "data_maturity_score": {
          "value": 2,
          "confidence": 0.75,
          "evidence": "Basic data engineering role with Snowflake mentioned but no modern practices like CI/CD, testing, monitoring, or governance tools. Very minimal job description suggests ad-hoc processes.",
          "source": "inferred"
        },
        "data_maturity_level": {
          "value": "developing",
          "confidence": 0.75,
          "evidence": "Score of 2 indicates developing stage with basic pipelines and some automation, but inconsistent practices based on minimal job description",
          "source": "inferred"
        },
        "maturity_signals": {
          "value": [],
          "confidence": 0.9,
          "evidence": "No modern data stack adoption, CI/CD practices, data quality testing, monitoring, or governance mentioned in job posting",
          "source": "pass1_derived"
        }
      },
      "red_flags_and_role_quality": {
        "scope_creep_score": {
          "value": 0.25,
          "confidence": 0.8,
          "evidence": "Role appears focused on data engineering with clear skill requirements (SQL, Python, Snowflake), no obvious scope creep into other domains",
          "source": "inferred"
        },
        "overtime_risk_score": {
          "value": 0.7,
          "confidence": 0.75,
          "evidence": "No work-life balance signals, benefits, or company culture mentioned. TCS consulting roles often involve long hours and tight deadlines. Onsite requirement in Cupertino suggests traditional corporate environment.",
          "source": "inferred"
        },
        "role_clarity": {
          "value": "vague",
          "confidence": 0.85,
          "evidence": "Very basic job description with minimal details about responsibilities, team structure, or day-to-day work. Lacks specific project details or technical challenges.",
          "source": "inferred"
        },
        "overall_red_flag_score": {
          "value": 0.65,
          "confidence": 0.78,
          "evidence": "Moderate risk due to vague role definition, no culture/work-life balance signals, and consulting company structure which often involves high pressure and unclear expectations",
          "source": "combined"
        }
      },
      "stakeholders_and_leadership": {
        "reporting_structure_clarity": {
          "value": "not_mentioned",
          "confidence": 0.95,
          "evidence": "No reporting structure, manager level, or team composition mentioned in job posting",
          "source": "pass1_derived"
        },
        "manager_level_inferred": {
          "value": "not_mentioned",
          "confidence": 0.9,
          "evidence": "No manager level or reporting structure information provided",
          "source": "pass1_derived"
        },
        "team_growth_velocity": {
          "value": "not_mentioned",
          "confidence": 0.9,
          "evidence": "No team growth, hiring velocity, or expansion plans mentioned",
          "source": "pass1_derived"
        },
        "team_composition": {
          "value": {
            "team_size": "not_mentioned",
            "de_count": "not_mentioned",
            "seniority_mix": "not_mentioned"
          },
          "confidence": 0.95,
          "evidence": "No team size, data engineer count, or seniority mix information provided",
          "source": "pass1_derived"
        },
        "reporting_structure": {
          "value": "not_mentioned",
          "confidence": 0.9,
          "evidence": "No reporting structure information provided",
          "source": "pass1_derived"
        },
        "cross_functional_embedded": {
          "value": false,
          "confidence": 0.7,
          "evidence": "No mention of embedded teams or cross-functional work, typical for traditional consulting arrangement",
          "source": "inferred"
        }
      },
      "tech_culture": {
        "work_life_balance_score": {
          "value": 0.3,
          "confidence": 0.8,
          "evidence": "No work-life balance signals, PTO policy, or flexible work arrangements mentioned. Onsite requirement in Cupertino suggests traditional corporate hours. TCS consulting often involves high-pressure deadlines.",
          "source": "inferred"
        },
        "growth_opportunities_score": {
          "value": 0.25,
          "confidence": 0.75,
          "evidence": "No learning budget, conference attendance, mentorship programs, or career advancement paths mentioned. Very minimal job description suggests limited growth focus.",
          "source": "inferred"
        },
        "tech_culture_score": {
          "value": 0.35,
          "confidence": 0.7,
          "evidence": "Basic tech stack mentioned (SQL, Python, Snowflake) but no modern engineering practices, code review culture, testing emphasis, or innovation signals",
          "source": "inferred"
        }
      },
      "tech_culture_assessment": {
        "tech_culture_signals": {
          "value": [],
          "confidence": 0.9,
          "evidence": "No open source, internal tools, tech blogs, conferences, hackathons, or innovation time mentioned",
          "source": "pass1_derived"
        },
        "dev_practices_mentioned": {
          "value": [],
          "confidence": 0.9,
          "evidence": "No development practices like code review, CI/CD, testing, monitoring, or incident response mentioned",
          "source": "pass1_derived"
        },
        "innovation_signals": {
          "value": "low",
          "confidence": 0.75,
          "evidence": "No innovation, experimentation, or staying current with industry trends mentioned. Very basic job description suggests maintenance-focused role",
          "source": "inferred"
        },
        "tech_debt_awareness": {
          "value": false,
          "confidence": 0.85,
          "evidence": "No mention of modernizing systems, improving code quality, or reducing technical debt",
          "source": "pass1_derived"
        }
      },
      "ai_ml_integration": {
        "ai_integration_level": {
          "value": "none",
          "confidence": 0.9,
          "evidence": "No AI, ML, or machine learning tools mentioned in job description",
          "source": "pass1_derived"
        },
        "ml_tools_expected": {
          "value": [],
          "confidence": 0.9,
          "evidence": "No ML/AI tools mentioned in job posting",
          "source": "pass1_derived"
        }
      },
      "competition_and_timing": {
        "hiring_urgency": {
          "value": "not_mentioned",
          "confidence": 0.9,
          "evidence": "No start date urgency, immediate need, or timeline mentioned",
          "source": "pass1_derived"
        },
        "competition_level": {
          "value": "medium",
          "confidence": 0.6,
          "evidence": "TCS is a large consulting firm that likely receives many applications. Onsite Cupertino location may limit some candidates but still competitive for Bay Area tech roles.",
          "source": "inferred"
        }
      },
      "company_context": {
        "company_stage_inferred": {
          "value": "enterprise",
          "confidence": 0.9,
          "evidence": "Tata Consultancy Services is a large, established Indian IT services company with global operations and enterprise clients",
          "source": "inferred"
        },
        "hiring_velocity": {
          "value": "steady",
          "confidence": 0.7,
          "evidence": "TCS typically has steady hiring for consulting roles, but no specific expansion signals mentioned",
          "source": "inferred"
        },
        "team_size_signals": {
          "value": "not_mentioned",
          "confidence": 0.9,
          "evidence": "No team size or data team composition mentioned",
          "source": "pass1_derived"
        },
        "funding_stage_signals": {
          "value": "public",
          "confidence": 0.95,
          "evidence": "Tata Consultancy Services is a publicly traded company (NSE: TCS)",
          "source": "inferred"
        },
        "role_creation_type": {
          "value": "not_mentioned",
          "confidence": 0.85,
          "evidence": "No indication if this is new headcount, backfill, or team expansion",
          "source": "pass1_derived"
        }
      }
    },
    "summary": {
      "strengths": [
        "Transparent salary range disclosed ($90k-$145k)",
        "Senior-level role with 8+ years experience requirement",
        "Modern data warehouse technology (Snowflake) mentioned",
        "Established company with job security (TCS is Fortune 500)"
      ],
      "concerns": [
        "Very basic and vague job description lacks detail",
        "No work-life balance, benefits, or company culture information",
        "Onsite requirement in expensive Cupertino location",
        "No growth opportunities, learning budget, or career development mentioned",
        "Low salary range for senior role in Bay Area tech market",
        "No reporting structure or team composition details"
      ],
      "best_fit_for": [
        "Data engineers seeking stable corporate environment over startup culture",
        "Candidates with strong SQL/Python skills looking for traditional consulting work",
        "Engineers prioritizing job security over rapid growth or innovation"
      ],
      "red_flags_to_probe": [
        "What is the actual team size and reporting structure?",
        "What are the typical work hours and overtime expectations?",
        "What benefits and PTO policy are offered?",
        "What specific projects and technologies will I be working with?",
        "Is there any career growth or learning opportunities?",
        "What is the client work environment and travel requirements?"
      ],
      "negotiation_leverage": [
        "Senior-level experience (8+ years) with in-demand skills (Snowflake)",
        "Bay Area cost of living may justify higher salary than range offered",
        "Strong Python and data pipeline experience is valuable in current market"
      ],
      "overall_assessment": "Basic consulting role at large IT services company with minimal job details provided. Suitable for candidates seeking stable corporate environment but concerning lack of transparency about role, team, and growth opportunities. Salary range appears low for senior Bay Area tech role. Main concerns are vague role definition and traditional consulting work environment.",
      "recommendation_score": 0.35,
      "recommendation_confidence": 0.8
    },
    "tokens": 10945,
    "input_tokens": 8248,
    "output_tokens": 2697,
    "cost": 0.013642000000000001
  }
}