{
  "metadata": {
    "timestamp": "2025-12-08 11:22:43",
    "job_posting_id": "4325939213",
    "job_title": "Senior Data Engineer (SQL, Python, Snowflake)",
    "company_name": "Tata Consultancy Services",
    "job_location": "Cupertino, CA",
    "pass_name": "pass2",
    "model_id": "minimax.minimax-m2"
  },
  "result": {
    "inference": {
      "seniority_and_role": {
        "seniority_level": {
          "value": "senior",
          "confidence": 0.92,
          "evidence": "Title explicitly states 'Senior Data Engineer' and requires 8+ years experience, which matches senior level expectations",
          "source": "combined"
        },
        "job_family": {
          "value": "data_engineer",
          "confidence": 0.95,
          "evidence": "Title is 'Data Engineer' with core focus on data pipeline creation and database management",
          "source": "pass1_derived"
        },
        "sub_specialty": {
          "value": "data_warehouse",
          "confidence": 0.75,
          "evidence": "Snowflake Database mentioned as key requirement, indicating warehouse-focused data engineering",
          "source": "inferred"
        },
        "leadership_expectation": {
          "value": "ic",
          "confidence": 0.65,
          "evidence": "No mentions of mentoring, team leadership, or direct reports; senior IC role without explicit people management requirements",
          "source": "inferred"
        }
      },
      "stack_and_cloud": {
        "primary_cloud": {
          "value": "not_mentioned",
          "confidence": 0.85,
          "evidence": "Snowflake mentioned but no specific cloud provider (AWS, Azure, GCP) explicitly stated",
          "source": "pass1_derived"
        },
        "secondary_clouds": {
          "value": [],
          "confidence": 0.9,
          "evidence": "No cloud providers mentioned beyond Snowflake, which is cloud-agnostic",
          "source": "pass1_derived"
        },
        "processing_paradigm": {
          "value": "not_mentioned",
          "confidence": 0.8,
          "evidence": "Data pipeline creation mentioned but no specific batch or streaming technologies or patterns described",
          "source": "pass1_derived"
        },
        "orchestrator_category": {
          "value": "not_mentioned",
          "confidence": 0.85,
          "evidence": "No orchestration tools (Airflow, Spark, etc.) mentioned in job description",
          "source": "pass1_derived"
        },
        "storage_layer": {
          "value": "warehouse",
          "confidence": 0.85,
          "evidence": "Snowflake explicitly mentioned as database requirement, indicating data warehouse focus",
          "source": "pass1_derived"
        }
      },
      "geo_and_work_model": {
        "remote_restriction": {
          "value": "not_mentioned",
          "confidence": 0.8,
          "evidence": "Location specified as Cupertino, CA but no work model (remote, hybrid, on-site) or restrictions mentioned",
          "source": "pass1_derived"
        },
        "timezone_focus": {
          "value": "not_mentioned",
          "confidence": 0.75,
          "evidence": "Cupertino, CA location suggests Pacific timezone but no specific timezone requirements stated",
          "source": "pass1_derived"
        },
        "relocation_required": {
          "value": false,
          "confidence": 0.7,
          "evidence": "No relocation package or requirements mentioned, location appears to be existing requirement rather than relocation",
          "source": "inferred"
        }
      },
      "visa_and_authorization": {
        "h1b_friendly": {
          "value": false,
          "confidence": 0.85,
          "evidence": "No visa sponsorship mentioned in job description, TCS typically handles this separately if available",
          "source": "pass1_derived"
        },
        "opt_cpt_friendly": {
          "value": false,
          "confidence": 0.75,
          "evidence": "No student visa or OPT/CPT mentions, and 8+ years experience requirement suggests experienced professionals only",
          "source": "inferred"
        },
        "citizenship_required": {
          "value": "not_mentioned",
          "confidence": 0.8,
          "evidence": "No citizenship or work authorization requirements explicitly stated in job posting",
          "source": "pass1_derived"
        }
      },
      "contract_and_compensation": {
        "w2_vs_1099": {
          "value": "w2",
          "confidence": 0.7,
          "evidence": "Tata Consultancy Services typically offers W2 full-time positions, salary range suggests employee rather than contractor role",
          "source": "inferred"
        },
        "benefits_level": {
          "value": "none_mentioned",
          "confidence": 0.9,
          "evidence": "No benefits, equity, PTO, or other compensation details mentioned in job description",
          "source": "pass1_derived"
        }
      },
      "career_development": {
        "growth_path_clarity": {
          "value": "not_mentioned",
          "confidence": 0.9,
          "evidence": "No career growth, advancement opportunities, or development paths mentioned",
          "source": "pass1_derived"
        },
        "mentorship_signals": {
          "value": "not_mentioned",
          "confidence": 0.9,
          "evidence": "No mentorship programs, working with senior staff, or collaborative environment mentioned",
          "source": "pass1_derived"
        },
        "promotion_path_mentioned": {
          "value": false,
          "confidence": 0.9,
          "evidence": "No promotion, advancement, or career progression opportunities mentioned",
          "source": "pass1_derived"
        },
        "internal_mobility_mentioned": {
          "value": false,
          "confidence": 0.9,
          "evidence": "No internal transfers, role changes, or mobility opportunities mentioned",
          "source": "pass1_derived"
        },
        "career_tracks_available": {
          "value": [],
          "confidence": 0.9,
          "evidence": "No career tracks, IC path, management path, or specialist tracks mentioned",
          "source": "pass1_derived"
        }
      },
      "requirements_classification": {
        "requirement_strictness": {
          "value": "high",
          "confidence": 0.75,
          "evidence": "Clear must-have skills listed (SQL, Python, Snowflake, communication) with no nice-to-have alternatives, indicating strict requirements",
          "source": "inferred"
        },
        "scope_definition": {
          "value": "clear",
          "confidence": 0.85,
          "evidence": "Focused job description with single clear role (Senior Data Engineer) and well-defined technical requirements",
          "source": "inferred"
        },
        "skill_inflation_detected": {
          "value": false,
          "confidence": 0.8,
          "evidence": "8+ years experience for senior level and skills (SQL, Python, Snowflake) are appropriate and realistic for the role level",
          "source": "inferred"
        }
      }
    },
    "tokens": 8279,
    "input_tokens": 5480,
    "output_tokens": 2799,
    "cost": 0.011078000000000001
  }
}