{
  "metadata": {
    "timestamp": "2025-12-08 15:32:36",
    "job_posting_id": "4348613426",
    "job_title": "Data Engineer-Business Intelligence",
    "company_name": "IBM",
    "job_location": "Pune, Maharashtra, India",
    "pass_name": "pass3",
    "model_id": "minimax.minimax-m2"
  },
  "result": {
    "analysis": {
      "company_maturity": {
        "data_maturity_score": {
          "value": 4,
          "confidence": 0.75,
          "evidence": "IBM is a large enterprise with established data practices, mentions modern cloud platforms (AWS, Google, Azure) and ETL tools, but focus on legacy BI tools like Cognos suggests mature but not cutting-edge practices",
          "source": "inferred"
        },
        "data_maturity_level": {
          "value": "managed",
          "confidence": 0.75,
          "evidence": "Score of 4 indicates managed level - IBM has established data governance, quality practices, and modern tooling integration, typical for large enterprise consulting environments",
          "source": "inferred"
        },
        "maturity_signals": {
          "value": [
            "cloud_native",
            "data_governance"
          ],
          "confidence": 0.7,
          "evidence": "Mentions multiple cloud platforms (AWS, Google, Azure) as preferred experience, and IBM's consulting delivery centers suggest established governance practices",
          "source": "pass1_derived"
        }
      },
      "red_flags_and_role_quality": {
        "scope_creep_score": {
          "value": 0.25,
          "confidence": 0.85,
          "evidence": "Well-defined BI engineer role focused on Cognos development, reporting, and data warehouse projects - no mixing of unrelated responsibilities like ML, DevOps, or backend development",
          "source": "inferred"
        },
        "overtime_risk_score": {
          "value": 0.65,
          "confidence": 0.75,
          "evidence": "IBM Consulting roles often involve client delivery pressure, tight deadlines, and project-based work which can lead to longer hours, especially in delivery centers",
          "source": "inferred"
        },
        "role_clarity": {
          "value": "clear",
          "confidence": 0.9,
          "evidence": "Very specific role focused on Cognos BI development, reporting, visualization, and data warehouse projects with clear technical requirements and responsibilities",
          "source": "inferred"
        },
        "overall_red_flag_score": {
          "value": 0.45,
          "confidence": 0.7,
          "evidence": "Moderate risk - well-defined role at established company but consulting delivery pressure and location restriction are notable concerns",
          "source": "combined"
        }
      },
      "stakeholders_and_leadership": {
        "reporting_structure_clarity": {
          "value": "vague",
          "confidence": 0.8,
          "evidence": "No specific manager or reporting structure mentioned, only refers to 'business and technical members of the team' in general terms",
          "source": "pass1_derived"
        },
        "manager_level_inferred": {
          "value": "not_mentioned",
          "confidence": 0.9,
          "evidence": "No mention of manager level, reporting structure, or leadership hierarchy in the job description",
          "source": "pass1_derived"
        },
        "team_growth_velocity": {
          "value": "not_mentioned",
          "confidence": 0.9,
          "evidence": "No mention of team expansion, hiring velocity, or growth plans in the job posting",
          "source": "pass1_derived"
        },
        "team_composition": {
          "value": {
            "team_size": "not specified",
            "de_count": "not specified",
            "seniority_mix": "mix of business and technical members"
          },
          "confidence": 0.7,
          "evidence": "Mentions working with 'business and technical members of the team' but no specific team size or composition details provided",
          "source": "pass1_derived"
        },
        "reporting_structure": {
          "value": "not_mentioned",
          "confidence": 0.9,
          "evidence": "No specific reporting structure, manager title, or organizational hierarchy mentioned in the job description",
          "source": "pass1_derived"
        },
        "cross_functional_embedded": {
          "value": false,
          "confidence": 0.75,
          "evidence": "Role appears to be within IBM Consulting delivery centers working on client projects rather than embedded in cross-functional product teams",
          "source": "inferred"
        }
      },
      "tech_culture": {
        "work_life_balance_score": {
          "value": 0.35,
          "confidence": 0.7,
          "evidence": "IBM Consulting delivery center roles often involve client delivery pressure, project deadlines, and consulting hours which can impact work-life balance",
          "source": "inferred"
        },
        "growth_opportunities_score": {
          "value": 0.3,
          "confidence": 0.75,
          "evidence": "No mention of career growth, learning opportunities, mentorship, or advancement paths - role appears focused on delivery rather than development",
          "source": "pass1_derived"
        },
        "tech_culture_score": {
          "value": 0.45,
          "confidence": 0.65,
          "evidence": "Mixed signals - mentions modern cloud platforms but focuses heavily on legacy BI tools like Cognos, no mention of modern engineering practices",
          "source": "combined"
        }
      },
      "tech_culture_assessment": {
        "tech_culture_signals": {
          "value": [
            "not_mentioned"
          ],
          "confidence": 0.9,
          "evidence": "No mention of open source contributions, tech blogs, conference speaking, hackathons, or innovation time in the job description",
          "source": "pass1_derived"
        },
        "dev_practices_mentioned": {
          "value": [
            "not_mentioned"
          ],
          "confidence": 0.9,
          "evidence": "No mention of code review, CI/CD, testing practices, monitoring, or other modern development practices",
          "source": "pass1_derived"
        },
        "innovation_signals": {
          "value": "low",
          "confidence": 0.7,
          "evidence": "Focus on maintenance and support of existing reporting systems, root cause analysis, and evolutionary maintenance suggests limited innovation opportunities",
          "source": "inferred"
        },
        "tech_debt_awareness": {
          "value": false,
          "confidence": 0.8,
          "evidence": "No mention of modernizing systems, reducing technical debt, or improving code quality - focus is on maintaining existing Cognos environments",
          "source": "inferred"
        }
      },
      "ai_ml_integration": {
        "ai_integration_level": {
          "value": "none",
          "confidence": 0.95,
          "evidence": "No mention of AI, ML, machine learning, or any AI/ML tools in the job description - purely focused on traditional BI and reporting",
          "source": "pass1_derived"
        },
        "ml_tools_expected": {
          "value": [],
          "confidence": 0.95,
          "evidence": "No ML/AI tools mentioned - role is focused on traditional BI tools like Cognos for reporting and visualization",
          "source": "pass1_derived"
        }
      },
      "competition_and_timing": {
        "hiring_urgency": {
          "value": "normal",
          "confidence": 0.8,
          "evidence": "No urgent language like 'immediate start' or 'ASAP' - appears to be standard IBM hiring process for consulting delivery center",
          "source": "inferred"
        },
        "competition_level": {
          "value": "medium",
          "confidence": 0.6,
          "evidence": "IBM is a well-known company, role requires specific Cognos skills which may limit candidate pool, but location in Pune may reduce competition compared to major tech hubs",
          "source": "inferred"
        }
      },
      "company_context": {
        "company_stage_inferred": {
          "value": "enterprise",
          "confidence": 0.95,
          "evidence": "IBM is a large, established enterprise company with global consulting operations and delivery centers",
          "source": "pass1_derived"
        },
        "hiring_velocity": {
          "value": "steady",
          "confidence": 0.7,
          "evidence": "IBM Consulting typically has steady hiring for delivery centers to support various client projects",
          "source": "inferred"
        },
        "team_size_signals": {
          "value": "not_mentioned",
          "confidence": 0.9,
          "evidence": "No specific team size mentioned in the job description",
          "source": "pass1_derived"
        },
        "funding_stage_signals": {
          "value": "public",
          "confidence": 0.95,
          "evidence": "IBM is a publicly traded, established enterprise company",
          "source": "pass1_derived"
        },
        "role_creation_type": {
          "value": "team_expansion",
          "confidence": 0.6,
          "evidence": "Consulting delivery centers typically expand teams based on client demand and project requirements",
          "source": "inferred"
        }
      }
    },
    "summary": {
      "strength_categories": [
        "established_company",
        "data_focused_role",
        "clear_requirements"
      ],
      "strength_details": [
        "IBM is a stable, established enterprise with global presence and consulting expertise",
        "Clear BI engineer role focused on Cognos development and data warehouse projects",
        "Specific technical requirements make it clear what skills are needed"
      ],
      "concern_categories": [
        "vague_requirements",
        "salary_not_disclosed",
        "limited_growth",
        "overtime_likely",
        "location_restriction"
      ],
      "concern_details": [
        "No salary, benefits, or compensation information disclosed",
        "No career growth, learning opportunities, or advancement path mentioned",
        "IBM Consulting delivery center roles often involve long hours and client delivery pressure",
        "Location restricted to Pune, India with no remote work options"
      ],
      "best_fit_categories": [
        "mid_level_engineers",
        "bi_engineers",
        "analytics_engineers"
      ],
      "best_fit_details": [
        "Mid-level data engineers with 3-5 years experience in BI and reporting",
        "Candidates with Cognos experience looking for stable enterprise roles",
        "Engineers seeking traditional BI focus rather than modern data engineering"
      ],
      "probe_categories": [
        "salary_range_details",
        "work_hour_expectations",
        "career_growth_path",
        "team_size_composition"
      ],
      "probe_details": [
        "Ask about salary range, benefits, and total compensation package",
        "Understand typical work hours and overtime expectations in consulting delivery",
        "Inquire about career progression and growth opportunities within IBM",
        "Ask about team structure and reporting relationships"
      ],
      "leverage_categories": [
        "rare_skill_match",
        "local_candidate"
      ],
      "leverage_details": [
        "Strong Cognos development and administration skills are specific and valuable",
        "Already located in Pune, Maharashtra, India - no relocation needed"
      ],
      "overall_assessment": "Stable enterprise BI role at IBM with clear technical focus on Cognos and data warehouse projects. Good for candidates seeking traditional BI work at established company. Main concerns are lack of compensation transparency, limited growth opportunities, and consulting delivery pressure. Location restriction to Pune may limit candidate pool.",
      "recommendation_score": 0.55,
      "recommendation_confidence": 0.75
    },
    "tokens": 12655,
    "input_tokens": 9479,
    "output_tokens": 3176,
    "cost": 0.015831
  }
}